ldtk_intgrid_creator/__init__.py
ldtk_intgrid_creator/__main__.py
ldtk_intgrid_creator/dict_templates.py
ldtk_intgrid_creator/group_creator.py
ldtk_intgrid_creator/level_creator.py
ldtk_intgrid_creator/rule_creator.py
ldtk_intgrid_creator/simplifier.py
ldtk_intgrid_creator/utilities.py
ldtk_intgrid_creator-0.2.0.dist-info/METADATA
ldtk_intgrid_creator-0.2.0.dist-info/WHEEL
ldtk_intgrid_creator-0.2.0.dist-info/entry_points.txt
ldtk_intgrid_creator-0.2.0.dist-info/top_level.txt
ldtk_intgrid_creator-0.2.0.dist-info/RECORD
