Metadata-Version: 2.1
Name: ldtk-intgrid-creator
Version: 0.2.0
Summary: Tool to generate IntGrid level for LDtk projects
Home-page: https://github.com/marinho/ldtk-int-layer-creator
Author: Marinho Brandao
Author-email: marinho@gmail.com
License: MIT
Platform: UNKNOWN
Classifier: License :: OSI Approved :: MIT License
Classifier: Programming Language :: Python :: 3
Classifier: Programming Language :: Python :: 3.7
